{"Year":["2000","2005","2011","2016","2000","2005","2011","2016"],"SERIES":["SP_DYN_MRBF15","SP_DYN_MRBF15","SP_DYN_MRBF15","SP_DYN_MRBF15","SP_DYN_MRBF18","SP_DYN_MRBF18","SP_DYN_MRBF18","SP_DYN_MRBF18"],"REF_AREA":["ET","ET","ET","ET","ET","ET","ET","ET"],"SEX":["_T","_T","_T","_T","_T","_T","_T","_T"],"AGE":["Y20T24","Y20T24","Y20T24","Y20T24","Y20T24","Y20T24","Y20T24","Y20T24"],"URBANISATION":["_T","_T","_T","_T","_T","_T","_T","_T"],"EDUCATION_LEV":["_T","_T","_T","_T","_T","_T","_T","_T"],"INCOME_WEALTH_QUANTILE":["_T","_T","_T","_T","_T","_T","_T","_T"],"UNIT_MEASURE":["PT","PT","PT","PT","PT","PT","PT","PT"],"UNIT_MULT":["0","0","0","0","0","0","0","0"],"REPORTING_TYPE":["N","N","N","N","N","N","N","N"],"TIME_DETAIL":["2000","2005","2011","2016","2000","2005","2011","2016"],"Value":[19.0,23.9,16.4,14.0,49.1,49.2,41.2,40.3]}